shieldid/__init__.py
shieldid/app.py
shieldid/builder.py
shieldid/device.py
shieldid/domain.py
shieldid/jwtutil.py
shieldid-0.1.4.dist-info/METADATA
shieldid-0.1.4.dist-info/WHEEL
shieldid-0.1.4.dist-info/top_level.txt
shieldid-0.1.4.dist-info/RECORD
