Metadata-Version: 2.1
Name: shieldid
Version: 0.1.4
Summary: utilities package for SHIELD ID(Security365 Cloud Idaas)
Home-page: https://github.com/jyjung/shieldid
Author: Jung JinYoung
Author-email: bungker@gmail.com
Classifier: Programming Language :: Python :: 3
Classifier: License :: OSI Approved :: MIT License
Classifier: Operating System :: OS Independent
Requires-Python: >=3.7
Requires-Dist: progressbar2
Requires-Dist: Requests
